better_profanity/__init__.py
better_profanity/alphabetic_unicode.json
better_profanity/better_profanity.py
better_profanity/constants.py
better_profanity/profanity_wordlist.txt
better_profanity/utils.py
better_profanity/varying_string.py
miladymumblepoliteness-0.7.0.data/data/unicode_characters/alphabetic_unicode.json
miladymumblepoliteness-0.7.0.data/data/wordlist/profanity_wordlist.txt
miladymumblepoliteness-0.7.0.dist-info/LICENSE
miladymumblepoliteness-0.7.0.dist-info/METADATA
miladymumblepoliteness-0.7.0.dist-info/WHEEL
miladymumblepoliteness-0.7.0.dist-info/top_level.txt
miladymumblepoliteness-0.7.0.dist-info/RECORD
